{"1:1":[["وَ","P","P|PREF|LEM:و"],["ٱل","P","DET|PREF|LEM:ال"],["سَّمَآءِ","N","ROOT:سمو|LEM:سَماء|F|GEN"]],"1:2":[["وَ","P","CONJ|PREF|LEM:و"],["ٱل","P","DET|PREF|LEM:ال"],["طَّارِقِ","N","ACT_PCPL|VF:1|ROOT:طرق|LEM:طارِق|M|GEN"]],"2:1":[["وَ","P","CONJ|PREF|LEM:و"],["مَآ","N","INTG|LEM:ما"]],"2:2":[["أَدْرَىٰ","V","PERF|VF:4|ROOT:دري|LEM:أَدْرَى|3MS"],["كَ","N","PRON|SUFF|2MS"]],"2:3":[["مَا","N","INTG|LEM:ما"]],"2:4":[["ٱل","P","DET|PREF|LEM:ال"],["طَّارِقُ","N","ACT_PCPL|VF:1|ROOT:طرق|LEM:طارِق|M|NOM"]],"3:1":[["ٱل","P","DET|PREF|LEM:ال"],["نَّجْمُ","N","ROOT:نجم|LEM:نَجْم|M|NOM"]],"3:2":[["ٱل","P","DET|PREF|LEM:ال"],["ثَّاقِبُ","N","ACT_PCPL|VF:1|ROOT:ثقب|LEM:ثاقِب|M|NOM|ADJ"]],"4:1":[["إِن","P","NEG|LEM:إِن"]],"4:2":[["كُلُّ","N","ROOT:كلل|LEM:كُلّ|M|NOM"]],"4:3":[["نَفْسٍ","N","ROOT:نفس|LEM:نَفْس|FS|INDEF|GEN"]],"4:4":[["لَّمَّا","P","EXP|LEM:لَمّا"]],"4:5":[["عَلَيْ","P","P|LEM:عَلَى"],["هَا","N","PRON|SUFF|3FS"]],"4:6":[["حَافِظٌ","N","ACT_PCPL|VF:1|ROOT:حفظ|LEM:حافِظ|M|INDEF|NOM"]],"5:1":[["فَ","P","CONJ|PREF|LEM:ف"],["لْ","P","IMPV|PREF|LEM:ل"],["يَنظُرِ","V","IMPF|VF:1|ROOT:نظر|LEM:نَظَرَ|3MS|MOOD:JUS"]],"5:2":[["ٱلْ","P","DET|PREF|LEM:ال"],["إِنسَٰنُ","N","ROOT:أنس|LEM:إِنسان|M|NOM"]],"5:3":[["مِ","P","P|LEM:مِن"],["مَّ","N","REL|LEM:ما"]],"5:4":[["خُلِقَ","V","PERF|VF:1|PASS|ROOT:خلق|LEM:خَلَقَ|3MS"]],"6:1":[["خُلِقَ","V","PERF|VF:1|PASS|ROOT:خلق|LEM:خَلَقَ|3MS"]],"6:2":[["مِن","P","P|LEM:مِن"]],"6:3":[["مَّآءٍ","N","ROOT:موه|LEM:ماء|M|INDEF|GEN"]],"6:4":[["دَافِقٍ","N","ACT_PCPL|VF:1|ROOT:دفق|LEM:دافِق|M|INDEF|GEN|ADJ"]],"7:1":[["يَخْرُجُ","V","IMPF|VF:1|ROOT:خرج|LEM:خَرَجَ|3MS|MOOD:IND"]],"7:2":[["مِنۢ","P","P|LEM:مِن"]],"7:3":[["بَيْنِ","N","ROOT:بين|LEM:بَيْن|GEN"]],"7:4":[["ٱل","P","DET|PREF|LEM:ال"],["صُّلْبِ","N","ROOT:صلب|LEM:صُلْب|M|GEN"]],"7:5":[["وَ","P","CONJ|PREF|LEM:و"],["ٱل","P","DET|PREF|LEM:ال"],["تَّرَآئِبِ","N","ROOT:ترب|LEM:تَرائِب|MP|GEN"]],"8:1":[["إِنَّ","P","ACC|LEM:إِنّ|FAM:إِنّ"],["هُۥ","N","PRON|SUFF|3MS"]],"8:2":[["عَلَىٰ","P","P|LEM:عَلَى"]],"8:3":[["رَجْعِ","N","ROOT:رجع|LEM:رَجْع|M|GEN"],["هِۦ","N","PRON|SUFF|3MS"]],"8:4":[["لَ","P","EMPH|PREF|LEM:ل"],["قَادِرٌ","N","ACT_PCPL|VF:1|ROOT:قدر|LEM:قادِر|M|INDEF|NOM"]],"9:1":[["يَوْمَ","N","T|ROOT:يوم|LEM:يَوْم|M|ACC"]],"9:2":[["تُبْلَى","V","IMPF|VF:1|PASS|ROOT:بلو|LEM:بَلَوْ|3FS|MOOD:IND"]],"9:3":[["ٱل","P","DET|PREF|LEM:ال"],["سَّرَآئِرُ","N","ROOT:سرر|LEM:سَرائِر|FP|NOM"]],"10:1":[["فَ","P","CONJ|PREF|LEM:ف"],["مَا","P","NEG|LEM:ما"]],"10:2":[["لَ","P","P|PREF|LEM:ل"],["هُۥ","N","PRON|3MS"]],"10:3":[["مِن","P","P|LEM:مِن"]],"10:4":[["قُوَّةٍ","N","ROOT:قوي|LEM:قُوَّة|F|INDEF|GEN"]],"10:5":[["وَ","P","CONJ|PREF|LEM:و"],["لَا","P","NEG|LEM:لا"]],"10:6":[["نَاصِرٍ","N","ACT_PCPL|VF:1|ROOT:نصر|LEM:ناصِر|M|INDEF|GEN"]],"11:1":[["وَ","P","P|PREF|LEM:و"],["ٱل","P","DET|PREF|LEM:ال"],["سَّمَآءِ","N","ROOT:سمو|LEM:سَماء|F|GEN"]],"11:2":[["ذَاتِ","N","LEM:ذُو|FS|GEN"]],"11:3":[["ٱل","P","DET|PREF|LEM:ال"],["رَّجْعِ","N","ROOT:رجع|LEM:رَجْع|M|GEN"]],"12:1":[["وَ","P","CONJ|PREF|LEM:و"],["ٱلْ","P","DET|PREF|LEM:ال"],["أَرْضِ","N","ROOT:أرض|LEM:أَرْض|F|GEN"]],"12:2":[["ذَاتِ","N","LEM:ذُو|FS|GEN"]],"12:3":[["ٱل","P","DET|PREF|LEM:ال"],["صَّدْعِ","N","ROOT:صدع|LEM:صَدْع|M|GEN"]],"13:1":[["إِنَّ","P","ACC|LEM:إِنّ|FAM:إِنّ"],["هُۥ","N","PRON|SUFF|3MS"]],"13:2":[["لَ","P","EMPH|PREF|LEM:ل"],["قَوْلٌ","N","VN|VF:1|ROOT:قول|LEM:قَوْل|M|INDEF|NOM"]],"13:3":[["فَصْلٌ","N","ROOT:فصل|LEM:فَصْل|M|INDEF|NOM|ADJ"]],"14:1":[["وَ","P","CONJ|PREF|LEM:و"],["مَا","P","NEG|LEM:ما|FAM:كَان"]],"14:2":[["هُوَ","N","PRON|3MS"]],"14:3":[["بِ","P","P|PREF|LEM:ب"],["ٱلْ","P","DET|PREF|LEM:ال"],["هَزْلِ","N","ROOT:هزل|LEM:هَزْل|M|GEN"]],"15:1":[["إِنَّ","P","ACC|LEM:إِنّ|FAM:إِنّ"],["هُمْ","N","PRON|SUFF|3MP"]],"15:2":[["يَكِيدُ","V","IMPF|VF:1|ROOT:كيد|LEM:كِيدُ|3MP|MOOD:IND"],["ونَ","N","PRON|SUFF|3MP"]],"15:3":[["كَيْدًا","N","ROOT:كيد|LEM:كَيْد|M|INDEF|ACC"]],"16:1":[["وَ","P","CONJ|PREF|LEM:و"],["أَكِيدُ","V","IMPF|VF:1|ROOT:كيد|LEM:كِيدُ|1S|MOOD:IND"]],"16:2":[["كَيْدًا","N","ROOT:كيد|LEM:كَيْد|M|INDEF|ACC"]],"17:1":[["فَ","P","REM|PREF|LEM:ف"],["مَهِّلِ","V","IMPV|VF:2|ROOT:مهل|LEM:مَهِّلِ|2MS"]],"17:2":[["ٱلْ","P","DET|PREF|LEM:ال"],["كَٰفِرِينَ","N","ACT_PCPL|VF:1|ROOT:كفر|LEM:كافِر|MP|ACC"]],"17:3":[["أَمْهِلْ","V","IMPV|VF:4|ROOT:مهل|LEM:أَمْهِلْ|2MS"],["هُمْ","N","PRON|SUFF|3MP"]],"17:4":[["رُوَيْدًۢا","N","ROOT:رود|LEM:رُوَيْد|M|INDEF|ACC"]]}